oak_runner-0.8.14.dist-info/METADATA
oak_runner-0.8.14.dist-info/WHEEL
oak_runner-0.8.14.dist-info/entry_points.txt
oak_runner/__init__.py
oak_runner/__main__.py
oak_runner/auth/__init__.py
oak_runner/auth/auth_parser.py
oak_runner/auth/auth_processor.py
oak_runner/auth/credentials/__init__.py
oak_runner/auth/credentials/fetch.py
oak_runner/auth/credentials/models.py
oak_runner/auth/credentials/provider.py
oak_runner/auth/credentials/transform.py
oak_runner/auth/credentials/validate.py
oak_runner/auth/models.py
oak_runner/evaluator.py
oak_runner/executor.py
oak_runner/executor/__init__.py
oak_runner/executor/action_handler.py
oak_runner/executor/operation_finder.py
oak_runner/executor/output_extractor.py
oak_runner/executor/parameter_processor.py
oak_runner/executor/server_processor.py
oak_runner/executor/step_executor.py
oak_runner/executor/success_criteria.py
oak_runner/extractor/openapi_extractor.py
oak_runner/http.py
oak_runner/models.py
oak_runner/runner.py
oak_runner/utils.py
oak_runner-0.8.14.dist-info/RECORD
