Metadata-Version: 2.1
Name: oak_runner
Version: 0.8.14
Summary: Execution libraries and test tools for Arazzo workflows and Open API operations
Author-Email: Jentic Labs <info@jenticlabs.com>
License: MIT
Requires-Python: >=3.10
Requires-Dist: pydantic>=2.0.0
Requires-Dist: pyyaml>=6.0
Requires-Dist: requests>=2.28.0
Requires-Dist: jsonpath-ng>=1.5.0
Requires-Dist: jsonpointer>=3.0.0
